[
  {
    "goal": {
      "id": "1",
      "title": "Armut in allen ihren Formen und überall beenden",
      "indicators": [
        
        {
          "id": "1-1-1",
          "title": "Anzahl der Personen die das Sozialhilfeportal nutzen",
          "description": "",
          "keywords": "",
          "href": "/SDGTK/de/1-1-1",
          "status": "notstarted"
        },
        {
          "id": "1-2-1",
          "title": "Anzahl der Repaircafes, Gemeinschaftswerkstätten und ReUse Shops in Treptow-Köpenick",
          "description": "",
          "keywords": "",
          "href": "/SDGTK/de/1-2-1",
          "status": "complete"
        },
        {
          "id": "1-3-1",
          "title": "Armutsgefährdungsquote in Treptow-Köpenick",
          "description": "",
          "keywords": "",
          "href": "/SDGTK/de/1-3-1",
          "status": "complete"
        }]
    }
  },
  {
    "goal": {
      "id": "2",
      "title": "Den Hunger beenden, Ernährungssicherheit und eine bessere Ernährung erreichen und eine nachhaltige Landwirtschaft fördern",
      "indicators": [
        
        {
          "id": "2-1-1",
          "title": "Öffentlich zugängliche Obstbäume und Beete",
          "description": "",
          "keywords": "",
          "href": "/SDGTK/de/2-1-1",
          "status": "complete"
        },
        {
          "id": "2-2-1",
          "title": "Fair zertifizierte Lebensmittel in der Berliner Schulverpflegung",
          "description": "",
          "keywords": "",
          "href": "/SDGTK/de/2-2-1",
          "status": "complete"
        },
        {
          "id": "2-3-1",
          "title": "Kilogramm gerettete Lebensmittel (Foodsharing)",
          "description": "",
          "keywords": "",
          "href": "/SDGTK/de/2-3-1",
          "status": "complete"
        }]
    }
  },
  {
    "goal": {
      "id": "3",
      "title": "Ein gesundes Leben für alle Menschen jeden Alters gewährleisten und ihr Wohlergehen fördern",
      "indicators": [
        
        {
          "id": "3-1-1",
          "title": "Stadtradeln - Anzahl der Personen die teilnehmen",
          "description": "",
          "keywords": "",
          "href": "/SDGTK/de/3-1-1",
          "status": "complete"
        },
        {
          "id": "3-1-2",
          "title": "Stadtradeln - Mit Fahrrad gefahrene Kilometer",
          "description": "",
          "keywords": "",
          "href": "/SDGTK/de/3-1-2",
          "status": "complete"
        },
        {
          "id": "3-1-3",
          "title": "Stadtradeln - Kilogramm CO2 eingespart",
          "description": "",
          "keywords": "",
          "href": "/SDGTK/de/3-1-3",
          "status": "complete"
        },
        {
          "id": "3-2-1",
          "title": "Relative Lärmbelastung in Treptow-Köpenick (Umweltgerechtigkeit)",
          "description": "",
          "keywords": "",
          "href": "/SDGTK/de/3-2-1",
          "status": "complete"
        },
        {
          "id": "3-3-1",
          "title": "Relative Luftbelastung in Treptow-Köpenick (Umweltgerechtigkeit)",
          "description": "",
          "keywords": "",
          "href": "/SDGTK/de/3-3-1",
          "status": "complete"
        },
        {
          "id": "3-3-2",
          "title": "Grenzwertüberschreitungen Luftverschmutzung in Treptow-Köpenick",
          "description": "",
          "keywords": "",
          "href": "/SDGTK/de/3-3-2",
          "status": "complete"
        }]
    }
  },
  {
    "goal": {
      "id": "4",
      "title": "Inklusive, gleichberechtigte und hochwertige Bildung gewährleisten und Möglichkeiten lebenslangen Lernens für alle fördern",
      "indicators": [
        
        {
          "id": "4-1-1",
          "title": "Anzahl der Schulen die pro Jahr an Lernkonferenz teilnehmen",
          "description": "",
          "keywords": "",
          "href": "/SDGTK/de/4-1-1",
          "status": "notstarted"
        },
        {
          "id": "4-2-1",
          "title": "Anzahl angebotener Fortbildungen zu 'Bildung für nachhaltige Entwicklung' (BNE) für das pädagogische Personal an Schulen in Treptow-Köpenick",
          "description": "",
          "keywords": "",
          "href": "/SDGTK/de/4-2-1",
          "status": "complete"
        },
        {
          "id": "4-3-1",
          "title": "Anzahl der Volkshochschul (VHS) Kurse zum Themenbereich Globales lernen, 'Bildung für nachhaltige Entwicklung' (BNE) und SDGs",
          "description": "",
          "keywords": "",
          "href": "/SDGTK/de/4-3-1",
          "status": "notstarted"
        },
        {
          "id": "4-4-1",
          "title": "Noch zu definieren",
          "description": "",
          "keywords": "",
          "href": "/SDGTK/de/4-4-1",
          "status": "notstarted"
        },
        {
          "id": "4-5-1",
          "title": "Projektteilnehmer des Projektes 'Umweltschule in Europa - Internationale Nachhaltigkeitsschule'",
          "description": "",
          "keywords": "",
          "href": "/SDGTK/de/4-5-1",
          "status": "complete"
        }]
    }
  },
  {
    "goal": {
      "id": "5",
      "title": "Geschlechtergleichstellung erreichen und alle Frauen und Mädchen zur Selbstbestimmung befähigen",
      "indicators": [
        
        {
          "id": "5-1-1",
          "title": "Anzahl der Schulen die am Projekttag teilnehmen",
          "description": "",
          "keywords": "",
          "href": "/SDGTK/de/5-1-1",
          "status": "notstarted"
        },
        {
          "id": "5-2-1",
          "title": "Anzahl der angebotenen Schulungen des Bezirksamts zum gendersensiblen Sprachgebrauch",
          "description": "",
          "keywords": "",
          "href": "/SDGTK/de/5-2-1",
          "status": "complete"
        },
        {
          "id": "5-3-1",
          "title": "Anzahl der Projekte, Anlaufpunkte und Beratungsangebote für Mädchen und junge Frauen in Treptow-Köpenick",
          "description": "",
          "keywords": "",
          "href": "/SDGTK/de/5-3-1",
          "status": "complete"
        },
        {
          "id": "5-4-1",
          "title": "Frauenanteil in den Leitungspositionen des höheren Dienstes",
          "description": "",
          "keywords": "",
          "href": "/SDGTK/de/5-4-1",
          "status": "complete"
        },
        {
          "id": "5-5-1",
          "title": "Frauenanteil in der Bezirksverordnetenversammlung (BVV) Treptow-Köpenicks",
          "description": "",
          "keywords": "",
          "href": "/SDGTK/de/5-5-1",
          "status": "complete"
        }]
    }
  },
  {
    "goal": {
      "id": "6",
      "title": "Verfügbarkeit und nachhaltige Bewirtschaftung von Wasser und Sanitärversorgung für alle gewährleisten",
      "indicators": [
        
        {
          "id": "6-1-1",
          "title": "Saprobie (organische Belastung) und Trophie (Nährstoffbelastung) des Müggelsee",
          "description": "",
          "keywords": "",
          "href": "/SDGTK/de/6-1-1",
          "status": "complete"
        },
        {
          "id": "6-2-1",
          "title": "Anzahl außerschulischer Einrichtungen der Natur- und Umweltbildung / Bildung für Nachhaltige Entwicklung (BNE)",
          "description": "",
          "keywords": "",
          "href": "/SDGTK/de/6-2-1",
          "status": "complete"
        },
        {
          "id": "6-3-1",
          "title": "Badegewässerqualität der Badestellen innerhalb des Bezirks Treptow-Köpenick",
          "description": "",
          "keywords": "",
          "href": "/SDGTK/de/6-3-1",
          "status": "complete"
        }]
    }
  },
  {
    "goal": {
      "id": "7",
      "title": "Zugang zu bezahlbarer, verlässlicher, nachhaltiger und moderner Energie für alle sichern",
      "indicators": [
        
        {
          "id": "7-1-1",
          "title": "Noch zu definieren",
          "description": "",
          "keywords": "",
          "href": "/SDGTK/de/7-1-1",
          "status": "notstarted"
        },
        {
          "id": "7-2-1",
          "title": "Anzahl der Photovoltaikanlagen auf bezirkseigenen Gebäuden",
          "description": "",
          "keywords": "",
          "href": "/SDGTK/de/7-2-1",
          "status": "complete"
        },
        {
          "id": "7-2-2",
          "title": "Stromerzeugung auf bezirkseigenen Gebäuden (kWh/Jahr)",
          "description": "",
          "keywords": "",
          "href": "/SDGTK/de/7-2-2",
          "status": "complete"
        },
        {
          "id": "7-3-1",
          "title": "Photovoltaik - Summe der Anlagen im Bezirk",
          "description": "",
          "keywords": "",
          "href": "/SDGTK/de/7-3-1",
          "status": "complete"
        },
        {
          "id": "7-3-2",
          "title": "Photovoltaik - Stromeinspeisung im Bezirk",
          "description": "",
          "keywords": "",
          "href": "/SDGTK/de/7-3-2",
          "status": "complete"
        },
        {
          "id": "7-3-3",
          "title": "Solarthermie - Summe der Anlagen im Bezirk",
          "description": "",
          "keywords": "",
          "href": "/SDGTK/de/7-3-3",
          "status": "complete"
        }]
    }
  },
  {
    "goal": {
      "id": "8",
      "title": "Dauerhaftes, breitenwirksames und nachhaltiges Wirtschaftswachstum, produktive Vollbeschäftigung und menschenwürdige Arbeit für alle fördern",
      "indicators": [
        
        {
          "id": "8-1-1",
          "title": "Anzahl der Unternehmen in Treptow-Köpenick die über ein gültiges Testat einer Gemeinwohl-Bilanz verfügen",
          "description": "",
          "keywords": "",
          "href": "/SDGTK/de/8-1-1",
          "status": "complete"
        },
        {
          "id": "8-2-1",
          "title": "Anzahl der Teilnehmenden am Mentoringprogramm",
          "description": "",
          "keywords": "",
          "href": "/SDGTK/de/8-2-1",
          "status": "notstarted"
        },
        {
          "id": "8-2-2",
          "title": "Anteil der Bewerber*innen mit Einwanderungsgeschichte",
          "description": "",
          "keywords": "",
          "href": "/SDGTK/de/8-2-2",
          "status": "notstarted"
        },
        {
          "id": "8-3-1",
          "title": "Anteil der Beschäftigten mit Einwanderungsgeschichte",
          "description": "",
          "keywords": "",
          "href": "/SDGTK/de/8-3-1",
          "status": "notstarted"
        },
        {
          "id": "8-3-2",
          "title": "Anteil der Beschäftigten mit Einwanderungsgeschichte in Führungspositionen der Kommunalverwaltung",
          "description": "",
          "keywords": "",
          "href": "/SDGTK/de/8-3-2",
          "status": "notstarted"
        },
        {
          "id": "8-4-1",
          "title": "Anzahl der kommunalen Einrichtungen in Treptow-Köpenick die über ein gültiges Testat einer Gemeinwohl-Bilanz verfügen",
          "description": "",
          "keywords": "",
          "href": "/SDGTK/de/8-4-1",
          "status": "complete"
        },
        {
          "id": "8-5-1",
          "title": "Bruttostundenverdienste und Verdienstunterschiede zwischen Frauen und Männern (Gender Pay Gap unbereinigt)",
          "description": "",
          "keywords": "",
          "href": "/SDGTK/de/8-5-1",
          "status": "complete"
        }]
    }
  },
  {
    "goal": {
      "id": "9",
      "title": "Eine widerstandsfähige Infrastruktur aufbauen, breitenwirksame und nachhaltige Industrialisierung fördern und Innovationen unterstützen",
      "indicators": [
        
        {
          "id": "9-1-1",
          "title": "Anzahl der Ladestationen für E-Autos",
          "description": "",
          "keywords": "",
          "href": "/SDGTK/de/9-1-1",
          "status": "complete"
        },
        {
          "id": "9-1-2",
          "title": "Stromverbrauch an Elektro-Ladesäulen",
          "description": "",
          "keywords": "",
          "href": "/SDGTK/de/9-1-2",
          "status": "complete"
        },
        {
          "id": "9-2-1",
          "title": "Anzahl öffentlicher Einrichtungen mit freiem WLAN Zugang",
          "description": "",
          "keywords": "",
          "href": "/SDGTK/de/9-2-1",
          "status": "complete"
        },
        {
          "id": "9-3-1",
          "title": "Breitband Verfügbarkeit Mbit/s in %",
          "description": "",
          "keywords": "",
          "href": "/SDGTK/de/9-3-1",
          "status": "complete"
        }]
    }
  },
  {
    "goal": {
      "id": "10",
      "title": "Ungleichheit in und zwischen Ländern verringern",
      "indicators": [
        
        {
          "id": "10-1-1",
          "title": "Anteil mehrsprachiger Informationsmaterialien",
          "description": "",
          "keywords": "",
          "href": "/SDGTK/de/10-1-1",
          "status": "notstarted"
        },
        {
          "id": "10-2-1",
          "title": "Anzahl der angebotenen Fortbildungen innerhalb der Verwaltung",
          "description": "",
          "keywords": "",
          "href": "/SDGTK/de/10-2-1",
          "status": "notstarted"
        },
        {
          "id": "10-3-1",
          "title": "Anzahl der Unternehmen in Treptow-Köpenick die eine Gemeinwohl-Bilanz durchführen",
          "description": "",
          "keywords": "",
          "href": "/SDGTK/de/10-3-1",
          "status": "complete"
        },
        {
          "id": "10-4-1",
          "title": "Gini-Koeffizient der Äquivalenzeinkommen in Treptow-Köpenick",
          "description": "",
          "keywords": "",
          "href": "/SDGTK/de/10-4-1",
          "status": "complete"
        }]
    }
  },
  {
    "goal": {
      "id": "11",
      "title": "Städte und Siedlungen inklusiv, sicher, widerstandsfähig und nachhaltig gestalten",
      "indicators": [
        
        {
          "id": "11-1-1",
          "title": "Anzahl der kostenlos ausleihbaren Lastenräder im Bezirk",
          "description": "",
          "keywords": "",
          "href": "/SDGTK/de/11-1-1",
          "status": "complete"
        },
        {
          "id": "11-1-2",
          "title": "Anzahl der Ausleihen von Lastenrädern",
          "description": "",
          "keywords": "",
          "href": "/SDGTK/de/11-1-2",
          "status": "complete"
        },
        {
          "id": "11-2-1",
          "title": "Anzahl der Abholstellen für Produkte Solidarischer Landwirtschaft (SoLaWi)",
          "description": "",
          "keywords": "",
          "href": "/SDGTK/de/11-2-1",
          "status": "complete"
        },
        {
          "id": "11-2-2",
          "title": "Anzahl der Imker im Bezirk",
          "description": "",
          "keywords": "",
          "href": "/SDGTK/de/11-2-2",
          "status": "complete"
        },
        {
          "id": "11-2-3",
          "title": "Anzahl der Bienenvölker im Bezirk",
          "description": "",
          "keywords": "",
          "href": "/SDGTK/de/11-2-3",
          "status": "complete"
        },
        {
          "id": "11-3-1",
          "title": "Anzahl Baumscheibenpatinnen und -paten",
          "description": "",
          "keywords": "",
          "href": "/SDGTK/de/11-3-1",
          "status": "complete"
        },
        {
          "id": "11-4-1",
          "title": "Häufigkeit der auf Wegen genutzten Verkehrsmittel in Treptow-Köpenick",
          "description": "",
          "keywords": "",
          "href": "/SDGTK/de/11-4-1",
          "status": "complete"
        },
        {
          "id": "11-5-1",
          "title": "Sport-, Freizeit- und Erholungsfläche in Treptow-Köpenick",
          "description": "",
          "keywords": "",
          "href": "/SDGTK/de/11-5-1",
          "status": "complete"
        },
        {
          "id": "11-5-2",
          "title": "Versorgung mit öffentlichen Grünflächen insgesamt",
          "description": "",
          "keywords": "",
          "href": "/SDGTK/de/11-5-2",
          "status": "complete"
        }]
    }
  },
  {
    "goal": {
      "id": "12",
      "title": "Nachhaltige Konsum- und Produktionsmuster sicherstellen",
      "indicators": [
        
        {
          "id": "12-1-1",
          "title": "Anzahl der Fortbildungen zu nachhaltiger und fairer Beschaffung pro Jahr",
          "description": "",
          "keywords": "",
          "href": "/SDGTK/de/12-1-1",
          "status": "notstarted"
        },
        {
          "id": "12-2-1",
          "title": "Anzahl der Kirchengemeinden die Teil der Fairtrade Town Kampagne sind",
          "description": "",
          "keywords": "",
          "href": "/SDGTK/de/12-2-1",
          "status": "complete"
        },
        {
          "id": "12-2-2",
          "title": "Anzahl der Kirchengemeinden mit dem Siegel 'Faire Gemeinde' im Bezirk",
          "description": "",
          "keywords": "",
          "href": "/SDGTK/de/12-2-2",
          "status": "complete"
        },
        {
          "id": "12-3-1",
          "title": "Stand der Zertifizierung der Kommune als Fairtrade Town",
          "description": "",
          "keywords": "",
          "href": "/SDGTK/de/12-3-1",
          "status": "complete"
        },
        {
          "id": "12-4-1",
          "title": "Anzahl der Fairtrade Schulen in Treptow-Köpenick",
          "description": "",
          "keywords": "",
          "href": "/SDGTK/de/12-4-1",
          "status": "complete"
        }]
    }
  },
  {
    "goal": {
      "id": "13",
      "title": "Umgehend Maßnahmen zur Bekämpfung des Klimawandels und seiner Auswirkungen ergreifen",
      "indicators": [
        
        {
          "id": "13-1-1",
          "title": "Stellenanteile für das Klimaschutzmanagement",
          "description": "",
          "keywords": "",
          "href": "/SDGTK/de/13-1-1",
          "status": "complete"
        },
        {
          "id": "13-1-2",
          "title": "Index Kommunaler Klimaschutz",
          "description": "",
          "keywords": "",
          "href": "/SDGTK/de/13-1-2",
          "status": "complete"
        },
        {
          "id": "13-2-1",
          "title": "Mittlere werktägliche Fahrradverkehrsstärke an der Zählstelle Treptow-Köpenick Kaisersteg",
          "description": "",
          "keywords": "",
          "href": "/SDGTK/de/13-2-1",
          "status": "complete"
        },
        {
          "id": "13-2-2",
          "title": "Anzahl der kostenlos ausleihbaren Lastenräder im Bezirk",
          "description": "",
          "keywords": "",
          "href": "/SDGTK/de/13-2-2",
          "status": "complete"
        },
        {
          "id": "13-2-3",
          "title": "Kilometer Radschnellwege im Bezirk",
          "description": "",
          "keywords": "",
          "href": "/SDGTK/de/13-2-3",
          "status": "complete"
        },
        {
          "id": "13-3-1",
          "title": "CO2-Emissionen aus dem Endenergieverbrauch (Verursacherbilanz)",
          "description": "",
          "keywords": "",
          "href": "/SDGTK/de/13-3-1",
          "status": "complete"
        }]
    }
  },
  {
    "goal": {
      "id": "14",
      "title": "Ozeane, Meere und Meeresressourcen im Sinne nachhaltiger Entwicklung erhalten und nachhaltig nutzen",
      "indicators": [
        
        {
          "id": "14-1-1",
          "title": "Rote Liste Einstufung der in Berliner Gewässern vorkommenden Fischarten",
          "description": "",
          "keywords": "",
          "href": "/SDGTK/de/14-1-1",
          "status": "complete"
        },
        {
          "id": "14-2-1",
          "title": "Anzahl der Anwohnerinnen die an der Sprechstunde der Ranger teilnehmen",
          "description": "",
          "keywords": "",
          "href": "/SDGTK/de/14-2-1",
          "status": "notstarted"
        },
        {
          "id": "14-3-1",
          "title": "Noch zu definieren",
          "description": "",
          "keywords": "",
          "href": "/SDGTK/de/14-3-1",
          "status": "notstarted"
        }]
    }
  },
  {
    "goal": {
      "id": "15",
      "title": "Landökosysteme schützen, wiederherstellen und ihre nachhaltige Nutzung fördern, Wälder nachhaltig bewirtschaften, Wüstenbildung bekämpfen, Bodendegradation beenden und umkehren und",
      "indicators": [
        
        {
          "id": "15-1-1",
          "title": "Index Kommunale Klimaanpassung",
          "description": "",
          "keywords": "",
          "href": "/SDGTK/de/15-1-1",
          "status": "complete"
        },
        {
          "id": "15-2-1",
          "title": "Anzahl der Teilnahmen des Bezirks an Netzwerktreffen und Veranstaltungen des „Akteursnetzwerk biologische Vielfalt“ pro Jahr",
          "description": "",
          "keywords": "",
          "href": "/SDGTK/de/15-2-1",
          "status": "complete"
        },
        {
          "id": "15-3-1",
          "title": "Naturschutzgebiete und Landschaftsschutzgebiete (Fläche in ha)",
          "description": "",
          "keywords": "",
          "href": "/SDGTK/de/15-3-1",
          "status": "complete"
        },
        {
          "id": "15-4-1",
          "title": "Noch zu definieren",
          "description": "",
          "keywords": "",
          "href": "/SDGTK/de/15-4-1",
          "status": "notstarted"
        }]
    }
  },
  {
    "goal": {
      "id": "16",
      "title": "Friedliche und inklusive Gesellschaften für eine nachhaltige Entwicklung fördern, allen Menschen Zugang zur Justiz ermöglichen und leistungsfähige, rechenschaftspflichtige und inklusive Institutionen auf allen Ebenen aufbauen",
      "indicators": [
        
        {
          "id": "16-1-1",
          "title": "Anzahl der partizipativen Veranstaltungen zum Thema SDGs des Bezirksamts Treptow-Köpenick pro Jahr",
          "description": "",
          "keywords": "",
          "href": "/SDGTK/de/16-1-1",
          "status": "complete"
        },
        {
          "id": "16-2-1",
          "title": "Anzahl der interreligiösen Veranstaltungen pro Jahr",
          "description": "",
          "keywords": "",
          "href": "/SDGTK/de/16-2-1",
          "status": "notstarted"
        },
        {
          "id": "16-3-1",
          "title": "Anzahl der rassistisch, antisemitisch, homophob und rechtsextrem geprägter Vorfälle pro Jahr in Treptow-Köpenick",
          "description": "",
          "keywords": "",
          "href": "/SDGTK/de/16-3-1",
          "status": "complete"
        },
        {
          "id": "16-4-1",
          "title": "Anzahl der Strukturen der Bürgerbeteiligung und Akteursvernetzung in den Bezirksregionenprofilen",
          "description": "",
          "keywords": "",
          "href": "/SDGTK/de/16-4-1",
          "status": "notstarted"
        }]
    }
  },
  {
    "goal": {
      "id": "17",
      "title": "Umsetzungsmittel stärken und die Globale Partnerschaft für nachhaltige Entwicklung mit neuem Leben erfüllen",
      "indicators": [
        
        {
          "id": "17-1-1",
          "title": "Anzahl der Veranstaltungen zum Thema Städtepartnerschaften des Bezirksamts Treptow-Köpenick pro Jahr",
          "description": "",
          "keywords": "",
          "href": "/SDGTK/de/17-1-1",
          "status": "complete"
        },
        {
          "id": "17-2-1",
          "title": "Menge verkaufter Packungen Fairtrade Kaffee 'Treptow-Köpenicker Bohne' pro Jahr",
          "description": "",
          "keywords": "",
          "href": "/SDGTK/de/17-2-1",
          "status": "complete"
        },
        {
          "id": "17-3-1",
          "title": "Städtepartnerschaften",
          "description": "",
          "keywords": "",
          "href": "/SDGTK/de/17-3-1",
          "status": "complete"
        },
        {
          "id": "17-3-2",
          "title": "Gemeindeprojekte und -partnerschaften",
          "description": "",
          "keywords": "",
          "href": "/SDGTK/de/17-3-2",
          "status": "complete"
        },
        {
          "id": "17-3-3",
          "title": "Schulpartnerschaften",
          "description": "",
          "keywords": "",
          "href": "/SDGTK/de/17-3-3",
          "status": "complete"
        },
        {
          "id": "17-3-4",
          "title": "Weitere zivilgesellschaftliche Projekte",
          "description": "",
          "keywords": "",
          "href": "/SDGTK/de/17-3-4",
          "status": "complete"
        },
        {
          "id": "17-3-5",
          "title": "Fairer Handel",
          "description": "",
          "keywords": "",
          "href": "/SDGTK/de/17-3-5",
          "status": "complete"
        },
        {
          "id": "17-4-1",
          "title": "Eine-Welt-Projekte und Partnerschaften im Bezirk Treptow-Köpenick",
          "description": "",
          "keywords": "",
          "href": "/SDGTK/de/17-4-1",
          "status": "complete"
        },
        {
          "id": "17-5-1",
          "title": "Noch zu definieren",
          "description": "",
          "keywords": "",
          "href": "/SDGTK/de/17-5-1",
          "status": "notstarted"
        },
        {
          "id": "17-6-1",
          "title": "Öffentliche Ausgaben für Entwicklungszusammenarbeit (Official Development Assistance, ODA)",
          "description": "",
          "keywords": "",
          "href": "/SDGTK/de/17-6-1",
          "status": "notstarted"
        }]
    }
  }]
